{"table":[{"Name":"Android developer","Gender":"Мужчина","Age":"19 лет","Employment":"Занятость:         проектная работа  частичная занятость  полная занятость","Schedule":"График работы:         удаленная работа  гибкий график  полный день  сменный график","Skills":["Android","Android SDK","ORM","Java","MySQL","Adobe Photoshop","Adobe Illustrator","Git"]},{"Name":"администратор","Gender":"Женщина","Age":"31 год","Employment":"Занятость:         полная занятость","Schedule":"График работы:         полный день","Skills":["excel","world,"]},{"Name":"Инженер-технолог","Gender":"Женщина","Age":"24 года","Employment":"Занятость:         полная занятость","Schedule":"График работы:         полный день","Skills":["нормативно-техническая документация","Участие в Тендерах","Ведение технической документации","Деловое общение","AutoCAD","Microsoft office","MS Word","MS Excel","Деловая переписка","Прием и распределение телефонных звонков","Телефонные переговоры","Подготовка конкурсной документации","Закупки","подготовка технико-коммерческих предложений","Подготовка коммерческих предложений","Участие в профессиональных выставках","Навыки переговоров"]},{"Name":"Мерчендайзер","Gender":"Мужчина","Age":"17 лет","Employment":"Занятость:         волонтерство  частичная занятость  полная занятость","Schedule":"График работы:         удаленная работа  гибкий график  полный день  сменный график","Skills":["Пользователь ПК","Консультирование","Грамотная речь","Стрессоустойчивость","Умение работать в команде"]},{"Name":"Оператор ПК, менеджер по персоналу,диспетчер,администратор,помощник юриста, инспектора по кадрам","Gender":"Женщина","Age":"33 года","Employment":"Занятость:         стажировка  полная занятость","Schedule":"График работы:         полный день","Skills":["знание Word, excel, internet","1 с"]},{"Name":"Экономист-маркетолог","Gender":"Женщина","Age":"20 лет","Employment":"Занятость:         полная занятость","Schedule":"График работы:         полный день  сменный график","Skills":["внимательность","аккуратность","трудолюбие","дисциплинированность","Грамотная речь","Грамотность","Работа в команде","Ориентация на результат","способность к обучению","скурпулёзность","MS PowerPoint","Internet","Google Chrome","Поиск информации в интернет","MS Word"]},{"Name":"Инженер-механик, инженер-конструктор","Gender":"Мужчина","Age":"29 лет","Employment":"Занятость:         полная занятость","Schedule":"График работы:         полный день","Skills":["Пользователь ПК","Техническое обслуживание","Ремонтные работы","производство","Умение работать в команде","Водительское удостоверение категории B","разработка чертежей","SolidWorks","AutoCAD","Знание устройства автомобиля","Контроль исправности оборудования","Капитальный ремонт"]},{"Name":"Механик по транспорту","Gender":"Мужчина","Age":"30 лет","Employment":"Занятость:         полная занятость","Schedule":"График работы:         полный день","Skills":["ремонт грузовых автомобилей"]},{"Name":"начальник складского комплекса, заведующий складом. Начальник смены. Заведующий хозяйством.","Gender":"Мужчина","Age":"58 лет","Employment":"Занятость:         полная занятость","Schedule":"График работы:         полный день","Skills":[]},{"Name":"Руководитель юридической (кадровой) службой","Gender":"Мужчина","Age":"44 года","Employment":"Занятость:         полная занятость","Schedule":"График работы:         полный день","Skills":[]},{"Name":"Системный администратор / помощник системного администратора ","Gender":"Мужчина","Age":"20 лет","Employment":"Занятость:         полная занятость","Schedule":"График работы:         полный день","Skills":["Продвинутый MS Excel (VBA)","Начальный уровень python","Тех. поддержка ПК","Редактор сайта"]},{"Name":"руководитель, начальник, управляющий, менеджер","Gender":"Мужчина","Age":"33 года","Employment":"Занятость:         полная занятость","Schedule":"График работы:         полный день","Skills":["Кадровая политика","Кадровое планирование","Управление персоналом","Организаторские навыки","Ведение переговоров","Кадровый менеджмент","Открытие торговых филиалов","Управление предприятием","Бизнес-планирование","Розничная торговля","Оптимизация численности персонала","Обучение и развитие","Управление товарными запасами","Организационное развитие","Антикризисное управление","Контроль дебиторской задолженности","Административное управление","Управленческие навыки","Руководство коллективом","Управленческая отчетность","Организационная структура","Стратегический менеджмент","Стратегическое планирование"]},{"Name":"Начальник участка (цеха)","Gender":"Мужчина","Age":"54 года","Employment":"Занятость:         проектная работа  полная занятость","Schedule":"График работы:         вахтовый метод  удаленная работа  гибкий график  полный день  сменный график","Skills":["Внедрение новых технологий и оборудования","Знание технологического процесса, оборудования, рецептур.","Контроль качества","Контроль складского хозяйства","Контроль трудовой дисциплины","Оптимизация логистических процессов","Оптимизация производственных процессов","Подбор производственного персонала","Поиск оптимальной работы предприятия","Поощрение лабораторных исследований","Постоянная учёба","Соблюдение безопасности труда","Соблюдение графика ППР оборудования и подвижного состава","Создание положительного морального климата в коллективе","Технический контроль производства","Управление производственным персоналом","Управление производством"]},{"Name":"Кладовщик 5 разряда, комплектовщик","Gender":"Женщина","Age":"28 лет","Employment":"Занятость:         полная занятость","Schedule":"График работы:         полный день","Skills":["Знание складских программ(wms, 1c,axapta,foxpro)","Бумажный документооборот","Работа с ТМЦ","Документальное сопровождение"]},{"Name":"Системный администратор","Gender":"Мужчина","Age":"40 лет","Employment":"Занятость:         частичная занятость  полная занятость","Schedule":"График работы:         вахтовый метод  удаленная работа  гибкий график  полный день  сменный график","Skills":[]},{"Name":"Менеджер по продаже запасных частей","Gender":"Мужчина","Age":"33 года","Employment":"Занятость:         полная занятость","Schedule":"График работы:         полный день  сменный график","Skills":["Работа в команде","Ориентация на результат","Управление цепочкой поставок","Пользователь ПК","Заключение договоров","Управленческая отчетность","Организаторские навыки","Работа с жалобами клиентов","Управленческие навыки","Управление командой","Руководство коллективом"]},{"Name":"Backend Java Developer","Gender":"Male","Age":"33 years","Employment":"Employment:         work placement  part time  full time","Schedule":"Work schedule:         flexible schedule  full day","Skills":["Atlassian Jira","Eclipse","Intellij IDEA","Java core","Java Servlets","JDeveloper","JSP","MySQL","Oracle DB","SVN","XML","Основы ANT","Основы MAVEN","MS SQL","JasperReport (iReport)","plan.io","SQL","ООП","Git","Linux","Redmine","MS SQL Server","Oracle Commerce (ATG)"]},{"Name":"Руководитель отдела, руководитель проектов","Gender":"Male","Age":"29 years","Employment":"Employment:         full time","Schedule":"Work schedule:         rotation based work  remote working  flexible schedule  full day  shift schedule","Skills":["LAN","TCP/IP","WAN","WLAN","Администрирование сайтов","Администрирование сетевого оборудования","Деловое общение","Управление персоналом","VMware","Unix","Hyper-V","Python","GNU/Linux","Системы видеонаблюдения","VoIP"]},{"Name":"Слесарь МСР,сварщик,механик-электрик,инженер-механик,сервисный инженер","Gender":"Мужчина","Age":"35 лет","Employment":"Занятость:         проектная работа  стажировка  частичная занятость  полная занятость","Schedule":"График работы:         удаленная работа  гибкий график  полный день  сменный график","Skills":["Техническое обслуживание","Слесарные работы","Монтаж оборудования","Чтение электросхем","3 группа по электробезопасности","Выездное обслуживание","Сварочные работы","Пуско-наладочные работы","Водительское удостоверение категории B","Техническая эксплуатация","Чтение чертежей","Ремонтные работы","КИПиА","Эксплуатация","производство","Знание устройства строительной,грузоподъемной,складской техники","Инициативность","саморазвитие","профессионализм","гидравлика","сварка,газорезка,плазменная резка","работа на металлообрабатывающих станках","педантичность","энергичность","Ответственность","пневматика","быстрая обучаемость","Покраска","управление вилочным погрузчиком"]},{"Name":"Инструктор тренажёрного зала","Gender":"Мужчина","Age":"20 лет","Employment":"Занятость:         частичная занятость  полная занятость","Schedule":"График работы:         гибкий график  полный день  сменный график","Skills":["Работа в команде","Обучение","Работа с людьми","Умение работать в команде","Грамотная речь"]}]}